glambox/__init__.py
glambox/version.py
glambox/_model/__init__.py
glambox/_model/components.py
glambox/_model/fit.py
glambox/_model/model.py
glambox/_model/simulation.py
glambox/_model/utils.py
glambox/analysis/__init__.py
glambox/analysis/_analysis_internal.py
glambox/analysis/analysis.py
glambox/plots/__init__.py
glambox/plots/_plots_internal.py
glambox/plots/_plots_unused.py
glambox/plots/plots.py
glambox-0.0.1.dist-info/LICENSE.txt
glambox-0.0.1.dist-info/METADATA
glambox-0.0.1.dist-info/WHEEL
glambox-0.0.1.dist-info/top_level.txt
glambox-0.0.1.dist-info/RECORD
