Metadata-Version: 2.1
Name: glambox
Version: 0.0.1
Summary: GLAMbox: A toolbox to fit the Gaze-weighted Linear Accumulator Model
Home-page: http://github.com/glamlab/glambox
Maintainer: Felix Molter <felixmolter@gmail.com>, Armin W. Thomas <athms.research@gmail.com>
Maintainer-email: glambox.berlin@gmail.com
License: MIT
Download-URL: https://github.com/glamlab/glambox/archive/0.0.1.tar.gz
Platform: UNKNOWN
Requires-Dist: matplotlib (==3.1.1)
Requires-Dist: numpy (==1.17.3)
Requires-Dist: pandas (==0.25.2)
Requires-Dist: pymc3 (==3.7)
Requires-Dist: scipy (==1.3.1)
Requires-Dist: seaborn (==0.9.0)
Requires-Dist: statsmodels (==0.10.1)
Requires-Dist: Theano (==1.0.4)
Requires-Dist: tqdm (==4.36.1)
